zarnevis/__init__.py
zarnevis/core.py
zarnevis-0.0.1.dist-info/LICENSE
zarnevis-0.0.1.dist-info/METADATA
zarnevis-0.0.1.dist-info/WHEEL
zarnevis-0.0.1.dist-info/top_level.txt
zarnevis-0.0.1.dist-info/RECORD
