Metadata-Version: 2.1
Name: zarnevis
Version: 0.0.1
Summary: Zarnevis, a tool for writing RTL text in computer vision projects
Home-page: https://github.com/prp-e/zarnevis
Author: Muhammadreza Haghiri
Author-email: <haghiri75@gmail.com>
License: MIT
Keywords: persian,arabic,rtl,text,cv,computer-vision
Platform: UNKNOWN
Classifier: Development Status :: 1 - Planning
Classifier: Intended Audience :: Developers
Classifier: Programming Language :: Python :: 3
Classifier: Operating System :: Unix
Classifier: Operating System :: MacOS :: MacOS X
Classifier: Operating System :: Microsoft :: Windows
Requires-Dist: numpy
Requires-Dist: pillow
Requires-Dist: arabic-reshaper
Requires-Dist: python-bidi
